gdax/FixClient.py
gdax/__init__.py
gdax/authenticated_client.py
gdax/order_book.py
gdax/public_client.py
gdax/websocket_client.py
gdax-1.0.6.dist-info/DESCRIPTION.rst
gdax-1.0.6.dist-info/METADATA
gdax-1.0.6.dist-info/RECORD
gdax-1.0.6.dist-info/WHEEL
gdax-1.0.6.dist-info/metadata.json
gdax-1.0.6.dist-info/top_level.txt
